behaverse/__init__.py
behaverse-0.0.1.dist-info/WHEEL
behaverse-0.0.1.dist-info/METADATA
behaverse-0.0.1.dist-info/RECORD
